InternetSpeedLogger/InternetSpeedLogger.py
InternetSpeedLogger/__init__.py
InternetSpeedLogger-1.3.0.dist-info/LICENSE
InternetSpeedLogger-1.3.0.dist-info/METADATA
InternetSpeedLogger-1.3.0.dist-info/WHEEL
InternetSpeedLogger-1.3.0.dist-info/entry_points.txt
InternetSpeedLogger-1.3.0.dist-info/top_level.txt
InternetSpeedLogger-1.3.0.dist-info/RECORD
