Metadata-Version: 2.1
Name: InternetSpeedLogger
Version: 1.3.0
Summary: A Python script that continuously monitors and logs your internet speed.
Author-email: Andreas Menzel <mail@andreas-menzel.com>
License: MIT License
Project-URL: Repository, https://github.com/Andreas-Menzel/InternetSpeedLogger
Project-URL: Bug Tracker, https://github.com/Andreas-Menzel/InternetSpeedLogger/issues
Keywords: speedtest,speedtest_cli,internet,internet speed,logger,monitor
Classifier: Programming Language :: Python :: 3
Classifier: License :: OSI Approved :: MIT License
Classifier: Operating System :: OS Independent
Requires-Python: >=3.6
License-File: LICENSE
Requires-Dist: matplotlib
Requires-Dist: pandas
Requires-Dist: speedtest-cli
